hdhelpers/__init__.py
hdhelpers/exceptions.py
hdhelpers/helper_functions.py
hdhelpers/plot_target_settings.py
hdhelpers/user_functions.py
hdhelpers-0.0.1.dist-info/METADATA
hdhelpers-0.0.1.dist-info/WHEEL
hdhelpers-0.0.1.dist-info/licenses/LICENSE
hdhelpers-0.0.1.dist-info/RECORD
