Metadata-Version: 2.4
Name: hdhelpers
Version: 0.0.1
Summary: Streamlines plotting and timezone handling in hetida designer components
Project-URL: homepage, https://fuseki.com/data-science/hetida-designer/
Project-URL: documentation, https://github.com/hetida/hetida-designer/tree/release/docs
Project-URL: repository, https://github.com/hetida/hetida-designer
Author-email: Christoph Dingel <cdingel@fuseki.com>, Steffen Wittkamp <swittkamp@fuseki.com>
License:  The MIT License (MIT)
License-File: LICENSE
Classifier: Development Status :: 2 - Pre-Alpha
Classifier: Environment :: Console
Classifier: Intended Audience :: Science/Research
Classifier: License :: OSI Approved :: MIT License
Classifier: Operating System :: Unix
Classifier: Programming Language :: Python :: 3.13
Classifier: Topic :: Scientific/Engineering
Requires-Python: >=3.13
Requires-Dist: pandas<3,>=2
Requires-Dist: plotly<7,>=6
Requires-Dist: pydantic<3,>=2
